pkuseg/__init__.py
pkuseg/config.py
pkuseg/data.py
pkuseg/download.py
pkuseg/feature_extractor.cpython-35m-darwin.so
pkuseg/feature_extractor.pyx
pkuseg/gradient.py
pkuseg/inference.cpython-35m-darwin.so
pkuseg/inference.pyx
pkuseg/model.py
pkuseg/optimizer.py
pkuseg/res_summarize.py
pkuseg/scorer.py
pkuseg/trainer.py
pkuseg/dicts/__init__.py
pkuseg/dicts/default.pkl
pkuseg/models/__init__.py
pkuseg/models/default/__init__.py
pkuseg/models/default/features.pkl
pkuseg/models/default/weights.npz
pkuseg/postag/__init__.py
pkuseg/postag/feature_extractor.cpython-35m-darwin.so
pkuseg/postag/feature_extractor.pyx
pkuseg/postag/model.py
pkuseg-0.0.25.dist-info/LICENSE
pkuseg-0.0.25.dist-info/METADATA
pkuseg-0.0.25.dist-info/WHEEL
pkuseg-0.0.25.dist-info/top_level.txt
pkuseg-0.0.25.dist-info/RECORD
