Metadata-Version: 2.1
Name: pkuseg
Version: 0.0.25
Summary: A small package for Chinese word segmentation
Home-page: https://github.com/lancopku/pkuseg-python
Author: Lanco
Author-email: luoruixuan97@pku.edu.cn
License: UNKNOWN
Platform: UNKNOWN
Classifier: Programming Language :: Python :: 3
Classifier: License :: Other/Proprietary License
Classifier: Operating System :: OS Independent
Requires-Dist: cython
Requires-Dist: numpy (>=1.16.0)
